importobot/__init__.py
importobot/__main__.py
importobot/config.py
importobot/context.py
importobot/exceptions.py
importobot/py.typed
importobot/telemetry.py
importobot/api/__init__.py
importobot/api/converters.py
importobot/api/suggestions.py
importobot/api/validation.py
importobot/caching/__init__.py
importobot/caching/base.py
importobot/caching/lru_cache.py
importobot/cli/__init__.py
importobot/cli/constants.py
importobot/cli/handlers.py
importobot/cli/parser.py
importobot/core/__init__.py
importobot/core/business_domains.py
importobot/core/constants.py
importobot/core/context_analyzer.py
importobot/core/conversion_strategies.py
importobot/core/converter.py
importobot/core/engine.py
importobot/core/field_definitions.py
importobot/core/interfaces.py
importobot/core/keyword_generator.py
importobot/core/keyword_loader.py
importobot/core/keywords_registry.py
importobot/core/multi_command_parser.py
importobot/core/parsers.py
importobot/core/pattern_matcher.py
importobot/core/schema_parser.py
importobot/core/zephyr_parsers.py
importobot/core/keywords/__init__.py
importobot/core/keywords/base_generator.py
importobot/core/keywords/generators/__init__.py
importobot/core/keywords/generators/api_keywords.py
importobot/core/keywords/generators/builtin_keywords.py
importobot/core/keywords/generators/database_keywords.py
importobot/core/keywords/generators/file_keywords.py
importobot/core/keywords/generators/operating_system_keywords.py
importobot/core/keywords/generators/ssh_keywords.py
importobot/core/keywords/generators/web_keywords.py
importobot/core/suggestions/__init__.py
importobot/core/suggestions/builtin_analyzer.py
importobot/core/suggestions/comparison_analyzer.py
importobot/core/suggestions/parameter_analyzer.py
importobot/core/suggestions/step_analyzer.py
importobot/core/suggestions/suggestion_engine.py
importobot/core/templates/__init__.py
importobot/core/templates/blueprints/__init__.py
importobot/core/templates/blueprints/default_builder.py
importobot-0.1.4.dist-info/licenses/LICENSE
importobot-0.1.4.dist-info/METADATA
importobot-0.1.4.dist-info/WHEEL
importobot-0.1.4.dist-info/entry_points.txt
importobot-0.1.4.dist-info/top_level.txt
importobot-0.1.4.dist-info/RECORD
