Metadata-Version: 2.4
Name: importobot
Version: 0.1.4
Summary: Automated test framework converter for migrating test cases from Zephyr, JIRA/Xray, and TestLink to Robot Framework format with bulk processing capabilities
Author-email: athola <noreply@github.com>
Maintainer-email: athola <noreply@github.com>
License-Expression: BSD-2-Clause
Project-URL: Homepage, https://github.com/athola/importobot
Project-URL: Repository, https://github.com/athola/importobot
Project-URL: Bug Tracker, https://github.com/athola/importobot/issues
Project-URL: Documentation, https://github.com/athola/importobot/wiki
Project-URL: Changelog, https://github.com/athola/importobot/blob/main/CHANGELOG.md
Keywords: testing,automation,robot-framework,test-conversion,zephyr,jira,xray,testlink
Classifier: Development Status :: 4 - Beta
Classifier: Intended Audience :: Developers
Classifier: Intended Audience :: Information Technology
Classifier: Operating System :: OS Independent
Classifier: Programming Language :: Python :: 3
Classifier: Programming Language :: Python :: 3.10
Classifier: Programming Language :: Python :: 3.11
Classifier: Programming Language :: Python :: 3.12
Classifier: Topic :: Software Development :: Testing
Classifier: Topic :: Software Development :: Quality Assurance
Classifier: Topic :: Utilities
Classifier: Environment :: Console
Classifier: Natural Language :: English
Classifier: Typing :: Typed
Requires-Python: >=3.10
License-File: LICENSE
Requires-Dist: robotframework>=6.0.0
Requires-Dist: robotframework-seleniumlibrary>=6.8.0
Requires-Dist: robotframework-sshlibrary>=3.8.0
Requires-Dist: robotframework-requests>=0.9.4
Requires-Dist: robotframework-databaselibrary>=2.3.2
Requires-Dist: psutil>=7.1.3
Requires-Dist: bleach>=6.3.0
Requires-Dist: asv>=0.6.5
Provides-Extra: viz
Requires-Dist: matplotlib>=3.10.7; extra == "viz"
Provides-Extra: analytics
Requires-Dist: numpy>=2.2.6; extra == "analytics"
Requires-Dist: pandas>=2.3.3; extra == "analytics"
Provides-Extra: demo
Requires-Dist: matplotlib>=3.10.7; extra == "demo"
Requires-Dist: numpy>=2.2.6; extra == "demo"
Requires-Dist: pandas>=2.3.3; extra == "demo"
Provides-Extra: advanced
Requires-Dist: scipy>=1.15.3; extra == "advanced"
Provides-Extra: medallion
Provides-Extra: enterprise
Requires-Dist: pandas>=2.3.3; extra == "enterprise"
Requires-Dist: numpy>=2.2.6; extra == "enterprise"
Provides-Extra: all
Requires-Dist: matplotlib>=3.10.7; extra == "all"
Requires-Dist: numpy>=2.2.6; extra == "all"
Requires-Dist: pandas>=2.3.3; extra == "all"
Dynamic: license-file
